impactrun/OpenApiSpecDiff.py
impactrun/__init__.py
impactrun/apispecs.py
impactrun/auth.py
impactrun/entry.py
impactrun/fuzzallspecs.py
impactrun/html_content_gen.py
impactrun/htmlreportgenerator.py
impactrun/impact_core.py
impactrun/reportcomp.py
impactrun/reportutil.py
impactrun/runall.py
impactrun/runconfig.py
impactrun/runonetest.py
impactrun/runperapi.py
impactrun/runperattack.py
impactrun/sumreport.py
impactrun/fuzzdb/README.md
impactrun/fuzzdb/_copyright.txt
impactrun/fuzzdb/fuzzdb-icon.png
impactrun/fuzzdb/fuzzdb.png
impactrun/fuzzdb/attack/README.md
impactrun/fuzzdb/attack/all-attacks/all-attacks-unix.txt
impactrun/fuzzdb/attack/all-attacks/all-attacks-win.txt
impactrun/fuzzdb/attack/all-attacks/all-attacks-xplatform.txt
impactrun/fuzzdb/attack/authentication/README.md
impactrun/fuzzdb/attack/authentication/php_magic_hashes.fuzz.txt
impactrun/fuzzdb/attack/business-logic/CommonDebugParamNames.txt
impactrun/fuzzdb/attack/business-logic/CommonMethodNames.txt
impactrun/fuzzdb/attack/business-logic/DebugParams.Json.fuzz.txt
impactrun/fuzzdb/attack/control-chars/HexValsAllBytes.txt
impactrun/fuzzdb/attack/control-chars/NullByteRepresentations.txt
impactrun/fuzzdb/attack/control-chars/imessage.txt
impactrun/fuzzdb/attack/control-chars/terminal-escape-codes.txt
impactrun/fuzzdb/attack/control-chars/true.txt
impactrun/fuzzdb/attack/disclosure-directory/directory-indexing-generic.txt
impactrun/fuzzdb/attack/disclosure-localpaths/unix/common-unix-httpd-log-locations.txt
impactrun/fuzzdb/attack/disclosure-source/README.md
impactrun/fuzzdb/attack/disclosure-source/source-disc-cmd-exec-traversal.txt
impactrun/fuzzdb/attack/disclosure-source/source-disclosure-generic.txt
impactrun/fuzzdb/attack/disclosure-source/source-disclosure-microsoft.txt
impactrun/fuzzdb/attack/email/invalid-email-addresses.txt
impactrun/fuzzdb/attack/email/valid-email-addresses.txt
impactrun/fuzzdb/attack/file-upload/README.md
impactrun/fuzzdb/attack/file-upload/alt-extensions-asp.txt
impactrun-2.2.3.dist-info/LICENSE.md
impactrun-2.2.3.dist-info/METADATA
impactrun-2.2.3.dist-info/WHEEL
impactrun-2.2.3.dist-info/entry_points.txt
impactrun-2.2.3.dist-info/top_level.txt
impactrun-2.2.3.dist-info/RECORD
