Metadata-Version: 2.1
Name: impactrun
Version: 2.2.3
Summary: To regenerate pytest fixtures and test methods dynamically from OpenAPI spec and Cloudvector APIShark events
Home-page: UNKNOWN
Author: Priyank Chheda
Author-email: priyank.chheda@imperva.com
License: UNKNOWN
Platform: UNKNOWN
Requires-Python: >=3.8,<4.0
License-File: LICENSE.md
Requires-Dist: PyYAML==6.0
Requires-Dist: autopep8==1.7.0
Requires-Dist: curlify==2.2.1
Requires-Dist: cvapianalyser==1.43.7
Requires-Dist: dictor==0.1.10
Requires-Dist: jinja2==3.1.2
Requires-Dist: nested-lookup==0.2.25
Requires-Dist: jsonschema==4.23.0
Requires-Dist: openapi-core==0.19.2
Requires-Dist: openapi-spec-validator==0.7.1
Requires-Dist: openapi-schema-validator==0.6.2
Requires-Dist: prance==23.6.21.0
Requires-Dist: pytest-cases==3.6.13
Requires-Dist: pytest-html==3.1.1
Requires-Dist: pytest-metadata==2.0.2
Requires-Dist: pytest-json==0.4.0
Requires-Dist: pytest-lazy-fixture==0.6.3
Requires-Dist: pytest-rerunfailures==10.2
Requires-Dist: pytest-testrail==2.9.0
Requires-Dist: pytest-timeout==2.1.0
Requires-Dist: pytest==7.1.3
Requires-Dist: requests==2.31.0
Requires-Dist: tqdm==4.64.1
Requires-Dist: MarkupSafe==2.0.1
Requires-Dist: validators==0.20.0
